pyproject.toml
autoeq/__init__.py
autoeq/__main__.py
autoeq/batch_processing.py
autoeq/constants.py
autoeq/csv.py
autoeq/frequency_response.py
autoeq/peq.py
autoeq/utils.py
webapp/ui/node_modules/big.js/LICENCE
webapp/ui/node_modules/duplexer/LICENCE
autoeq-4.1.1.dist-info/METADATA
autoeq-4.1.1.dist-info/WHEEL
autoeq-4.1.1.dist-info/licenses/LICENSE
autoeq-4.1.1.dist-info/RECORD
