Metadata-Version: 2.1
Name: autoeq
Version: 4.1.1
Summary: Automatic headphone equalizer config generator
Project-URL: Homepage, https://github.com/jaakkopasanen/AutoEq
Project-URL: Bug Tracker, https://github.com/jaakkopasanen/AutoEq/issues
Author-email: Jaakko Pasanen <jaakko.o.pasanen@gmail.com>
License-File: LICENSE
Classifier: License :: OSI Approved :: MIT License
Classifier: Operating System :: OS Independent
Classifier: Programming Language :: Python :: 3
Requires-Python: <3.12,>=3.8
Requires-Dist: matplotlib~=3.7.3
Requires-Dist: numpy~=1.24.4
Requires-Dist: pillow~=10.0.1
Requires-Dist: pyyaml~=6.0
Requires-Dist: scipy~=1.10.1
Requires-Dist: soundfile~=0.12.1
Requires-Dist: tabulate~=0.9.0
Requires-Dist: tqdm~=4.66.1
